CHANGES.rst
CONTRIBUTORS.rst
LICENSE.txt
MANIFEST.in
README.rst
buildout.cfg
setup.py
shootout.cfg
todo.rst
src/newt/__init__.py
src/newt.db.egg-info/PKG-INFO
src/newt.db.egg-info/SOURCES.txt
src/newt.db.egg-info/dependency_links.txt
src/newt.db.egg-info/entry_points.txt
src/newt.db.egg-info/namespace_packages.txt
src/newt.db.egg-info/not-zip-safe
src/newt.db.egg-info/requires.txt
src/newt.db.egg-info/top_level.txt
src/newt/db/__init__.py
src/newt/db/_adapter.py
src/newt/db/_db.py
src/newt/db/_object.py
src/newt/db/_ook.py
src/newt/db/_util.py
src/newt/db/component.py
src/newt/db/component.xml
src/newt/db/follow.py
src/newt/db/jsonpickle.py
src/newt/db/search.py
src/newt/db/updater.py
src/newt/db/zodburi.py
src/newt/db/tests/__init__.py
src/newt/db/tests/base.py
src/newt/db/tests/testadapter.py
src/newt/db/tests/testdbconfig.py
src/newt/db/tests/testdocs.py
src/newt/db/tests/testfollow.py
src/newt/db/tests/testjsonpickle.py
src/newt/db/tests/testsearch.py
src/newt/db/tests/testupdater.py
src/newt/db/tests/testzodburi.py